napari_apr_viewer/_APRViewer.py
napari_apr_viewer/__init__.py
napari_apr_viewer/_convert_apr_to_image.py
napari_apr_viewer/_convert_image_to_apr.py
napari_apr_viewer/_dock_widgets.py
napari_apr_viewer/_reader.py
napari_apr_viewer/_threshold.py
napari_apr_viewer/_utils.py
napari_apr_viewer/_version.py
napari_apr_viewer/_writer.py
napari_apr_viewer/_tests/__init__.py
napari_apr_viewer/_tests/test_dock_widget.py
napari_apr_viewer/_tests/test_reader.py
napari_apr_viewer/_tests/test_writer.py
napari_apr_viewer-1.0.1.dist-info/LICENSE
napari_apr_viewer-1.0.1.dist-info/METADATA
napari_apr_viewer-1.0.1.dist-info/WHEEL
napari_apr_viewer-1.0.1.dist-info/entry_points.txt
napari_apr_viewer-1.0.1.dist-info/top_level.txt
napari_apr_viewer-1.0.1.dist-info/RECORD
