Metadata-Version: 2.1
Name: napari-apr-viewer
Version: 1.0.1
Summary: A simple plugin to view APR images in napari
Author: Joel Jonsson
Author-email: jonsson@mpi-cbg.de
License: Apache-2.0
Classifier: Development Status :: 2 - Pre-Alpha
Classifier: Intended Audience :: Developers
Classifier: Framework :: napari
Classifier: Topic :: Software Development :: Testing
Classifier: Programming Language :: Python
Classifier: Programming Language :: Python :: 3
Classifier: Programming Language :: Python :: 3.8
Classifier: Programming Language :: Python :: 3.9
Classifier: Programming Language :: Python :: 3.10
Classifier: Programming Language :: Python :: 3.11
Classifier: Operating System :: OS Independent
Classifier: License :: OSI Approved :: Apache Software License
Requires-Python: >=3.8
License-File: LICENSE
Requires-Dist: numpy
Requires-Dist: pyapr >=1.0.0rc1
Requires-Dist: napari
Requires-Dist: napari-plugin-engine >=0.1.4
Requires-Dist: qtpy
Requires-Dist: magicgui
